LICENSE.txt
MANIFEST.in
Makefile
README.md
README.rst
base-libpycoram.mk
base.mk
default.config
mem-incr.hex
setup.cfg
setup.py
c_lib/cma.h
c_lib/pycoram.h
c_lib/umem.h
docker/Dockerfile
examples/Makefile
examples/app/Makefile
examples/app/dijkstra/Makefile
examples/app/dijkstra/cthread_dijkstra.py
examples/app/dijkstra/cthread_heap.py
examples/app/dijkstra/cthread_read_edge.py
examples/app/dijkstra/cthread_read_node.py
examples/app/dijkstra/cthread_write_node_update.py
examples/app/dijkstra/cthread_write_node_visited.py
examples/app/dijkstra/dijkstra.v
examples/app/dijkstra/frontier.v
examples/app/dijkstra/heap.v
examples/app/dijkstra/iv-wave.sav
examples/app/dijkstra/mem-incr.hex
examples/app/dijkstra/read_edge.v
examples/app/dijkstra/read_node.v
examples/app/dijkstra/testbench.v
examples/app/dijkstra/vcs-wave.sav
examples/app/dijkstra/write_node_update.v
examples/app/dijkstra/write_node_visited.v
examples/app/dijkstra/data/Makefile
examples/app/dijkstra/data/USA-road-d.CAL.gr
examples/app/dijkstra/data/USA-road-d.COL.gr
examples/app/dijkstra/data/USA-road-d.NY.gr
examples/app/dijkstra/data/bin2hex.py
examples/app/dijkstra/data/convert.py
examples/app/dijkstra/data/memgen.py
examples/app/dijkstra/data/memgen_random.py
examples/app/dijkstra/data/n2048.gr
examples/app/dijkstra/software/Makefile
examples/app/dijkstra/software/c-heap-base/Makefile
examples/app/dijkstra/software/c-heap-base/heap.h
examples/app/dijkstra/software/c-heap-base/main.c
examples/app/dijkstra/software/c-heap-base/test.c
examples/app/dijkstra/software/c-heap-opt/Makefile
examples/app/dijkstra/software/c-heap-opt/heap.h
examples/app/dijkstra/software/c-heap-opt/main.c
examples/app/dijkstra/software/c-heap-opt/test.c
examples/app/dijkstra/software/c-heap-opt-hash/Makefile
examples/app/dijkstra/software/c-heap-opt-hash/heap.h
examples/app/dijkstra/software/c-heap-opt-hash/main.c
examples/app/dijkstra/software/c-heap-opt-random/Makefile
examples/app/dijkstra/software/c-heap-opt-random/heap.h
pycoram.egg-info/PKG-INFO
pycoram.egg-info/SOURCES.txt
pycoram.egg-info/dependency_links.txt
pycoram.egg-info/entry_points.txt
pycoram.egg-info/requires.txt
pycoram.egg-info/top_level.txt
