Metadata-Version: 1.0
Name: pycoram
Version: 1.0.1
Summary: Python-based Portable IP-core Synthesis Framework for FPGA-based Computing
Home-page: https://github.com/PyHDI/PyCoRAM
Author: Shinya Takamaeda-Yamazaki
Author-email: shinya.takamaeda_at_gmail_com
License: Apache License 2.0
Keywords: FPGA,Verilog HDL,High-Level Synthesis
Platform: UNKNOWN
